xmlable/__init__.py
xmlable/_errors.py
xmlable/_io.py
xmlable/_lxml_helpers.py
xmlable/_manual.py
xmlable/_user.py
xmlable/_utils.py
xmlable/_xmlify.py
xmlable/_xobject.py
xmlable/py.typed
xmlable-2.0.7.dist-info/METADATA
xmlable-2.0.7.dist-info/WHEEL
xmlable-2.0.7.dist-info/licenses/LICENSE
xmlable-2.0.7.dist-info/RECORD
