Metadata-Version: 2.4
Name: xmlable
Version: 2.0.7
Summary: A decorator for generating xsd, xml and parsers from dataclasses
Project-URL: Homepage, https://github.com/OliverKillane/xmlable
Project-URL: Bug Tracker, https://github.com/OliverKillane/xmlable/issues
Project-URL: Source, https://github.com/OliverKillane/xmlable
Author-email: Oliver Killane <oliverkillane.business@gmail.com>
License: MIT License
License-File: LICENSE
Keywords: lxml,xml,xmlschema,xsd
Classifier: License :: OSI Approved :: MIT License
Classifier: Operating System :: OS Independent
Classifier: Programming Language :: Python :: 3
Requires-Python: >=3.11
Requires-Dist: lxml-stubs==0.5.1
Requires-Dist: lxml==5.3.1
Requires-Dist: pyhumps==3.8.0
Requires-Dist: termcolor==2.5.0
Provides-Extra: dev
Requires-Dist: black==25.1.0; extra == 'dev'
Requires-Dist: mypy==1.15.0; extra == 'dev'
Requires-Dist: pytest==8.3.5; extra == 'dev'
